txkube/__init__.py
txkube/_authentication.py
txkube/_compat.py
txkube/_exception.py
txkube/_interface.py
txkube/_invariants.py
txkube/_memory.py
txkube/_metadata.py
txkube/_model.py
txkube/_network.py
txkube/_swagger.py
txkube/extra-1.5.json
txkube/kubernetes-1.5.json
txkube/test/__init__.py
txkube/test/_compat.py
txkube/test/test_authentication.py
txkube/test/test_compat.py
txkube/test/test_invariants.py
txkube/test/test_memory.py
txkube/test/test_model.py
txkube/test/test_network.py
txkube/test/test_swagger.py
txkube/testing/__init__.py
txkube/testing/_eliot.py
txkube/testing/_testcase.py
txkube/testing/integration.py
txkube/testing/matchers.py
txkube/testing/strategies.py
txkube/testing/test/__init__.py
txkube/testing/test/test_eliot.py
txkube/testing/test/test_matchers.py
txkube-0.3.0.dist-info/DESCRIPTION.rst
txkube-0.3.0.dist-info/METADATA
txkube-0.3.0.dist-info/RECORD
txkube-0.3.0.dist-info/WHEEL
txkube-0.3.0.dist-info/metadata.json
txkube-0.3.0.dist-info/top_level.txt
