Metadata-Version: 2.0
Name: txkube
Version: 0.3.0
Summary: A Twisted-based Kubernetes client.
Home-page: https://github.com/LeastAuthority/txkube
Author: txkube Developers
License: MIT
Platform: UNKNOWN
Provides-Extra: dev
Requires-Dist: zope.interface
Requires-Dist: attrs
Requires-Dist: pyrsistent (>=0.12.2)
Requires-Dist: incremental
Requires-Dist: twisted[tls] (>=17.9.0)
Requires-Dist: pem
Requires-Dist: eliot
Requires-Dist: python-dateutil
Requires-Dist: pykube
Requires-Dist: treq
Requires-Dist: klein
Provides-Extra: dev
Requires-Dist: testtools; extra == 'dev'
Requires-Dist: hypothesis; extra == 'dev'
Requires-Dist: eliot-tree (>=17.1.0); extra == 'dev'
